cdga_roasters/__init__.py
CDGARoasters-0.1.dist-info/METADATA
CDGARoasters-0.1.dist-info/WHEEL
CDGARoasters-0.1.dist-info/top_level.txt
CDGARoasters-0.1.dist-info/RECORD
