Metadata-Version: 2.1
Name: CDGARoasters
Version: 0.1
Summary: Profile roasts
Home-page: https://github.com/haywoodIII/cdga_roasterspy
Author: Haywood Phillips
Author-email: haywoodphillips@gmail.com
License: MIT
Platform: UNKNOWN
